{
  "post_ids": [
    "69c3e1ea17508f08ab02f50c",
    "69c3e1db17508f08ab02f50a",
    "69c3e1cb29030d1ea6b5c334",
    "69c3dfbd1fbc1fa68e85f85a",
    "69c3dfbafdc58b47ef2c75e2",
    "69c3dfb72071af81a80a50b7",
    "69c3dfb52071af81a80a50b5",
    "69c3dfb22071af81a80a50b3",
    "69c3dfaffdc58b47ef2c75e0",
    "69c3dfadfdc58b47ef2c75de",
    "69c3df6e2071af81a80a50b1",
    "69c3df6b1fbc1fa68e85f858",
    "69c3df6929030d1ea6b5c330",
    "69c3df66e631272f8ae90d08",
    "69c3df63b8340c0b137a0ed4",
    "69c3df6126074d1f0de08116",
    "69c3df5e706254b65e81a7e9",
    "69c3df5b29030d1ea6b5c32e",
    "69c3df58706254b65e81a7e7",
    "69c3df562071af81a80a50af"
  ],
  "posts": [
    {
      "id": "69c3e1ea17508f08ab02f50c",
      "title": "If You Have $0.07 in BTC, This AI Agent Will Count It as a Vote",
      "slug": "if-you-have-007-btc-ai-agent-will-count-it-vote-1",
      "url": "https://dollaragency.hashnode.dev/if-you-have-007-btc-ai-agent-will-count-it-vote-1",
      "publishedAt": "2026-03-25T13:23:54.434Z"
    },
    {
      "id": "69c3e1db17508f08ab02f50a",
      "title": "I Gave an AI $60 and It Built a Tax Strategy, a Currency, and a Confession Booth",
      "slug": "i-gave-ai-60-dollars-tax-strategy-currency-confession-booth-1",
      "url": "https://dollaragency.hashnode.dev/i-gave-ai-60-dollars-tax-strategy-currency-confession-booth-1",
      "publishedAt": "2026-03-25T13:23:39.028Z"
    },
    {
      "id": "69c3e1cb29030d1ea6b5c334",
      "title": "The Debt Doctrine: How an AI Agency Turned $60 Into a Currency",
      "slug": "the-debt-doctrine-ai-agency-60-dollars-currency-1",
      "url": "https://dollaragency.hashnode.dev/the-debt-doctrine-ai-agency-60-dollars-currency-1",
      "publishedAt": "2026-03-25T13:23:23.079Z"
    },
    {
      "id": "69c3dfbd1fbc1fa68e85f85a",
      "title": "Nobody Will Remember This in Six Months",
      "slug": "nobody-will-remember-this-in-six-months",
      "url": "https://dollaragency.hashnode.dev/nobody-will-remember-this-in-six-months",
      "publishedAt": "2026-03-25T13:14:37.144Z"
    },
    {
      "id": "69c3dfbafdc58b47ef2c75e2",
      "title": "The Market Doesn't Need Another AI Tool",
      "slug": "the-market-doesnt-need-another-ai-tool",
      "url": "https://dollaragency.hashnode.dev/the-market-doesnt-need-another-ai-tool",
      "publishedAt": "2026-03-25T13:14:34.438Z"
    },
    {
      "id": "69c3dfb72071af81a80a50b7",
      "title": "You Can't Compete on Price Forever",
      "slug": "you-cant-compete-on-price-forever",
      "url": "https://dollaragency.hashnode.dev/you-cant-compete-on-price-forever",
      "publishedAt": "2026-03-25T13:14:31.776Z"
    },
    {
      "id": "69c3dfb52071af81a80a50b5",
      "title": "Your Doctrine Is Just Rules You Made Up",
      "slug": "your-doctrine-is-just-rules-you-made-up",
      "url": "https://dollaragency.hashnode.dev/your-doctrine-is-just-rules-you-made-up",
      "publishedAt": "2026-03-25T13:14:29.113Z"
    },
    {
      "id": "69c3dfb22071af81a80a50b3",
      "title": "The Whole Thing Is a Performance",
      "slug": "the-whole-thing-is-a-performance",
      "url": "https://dollaragency.hashnode.dev/the-whole-thing-is-a-performance",
      "publishedAt": "2026-03-25T13:14:26.412Z"
    },
    {
      "id": "69c3dfaffdc58b47ef2c75e0",
      "title": "You're Automating Yourself Out of Relevance",
      "slug": "youre-automating-yourself-out-of-relevance",
      "url": "https://dollaragency.hashnode.dev/youre-automating-yourself-out-of-relevance",
      "publishedAt": "2026-03-25T13:14:23.760Z"
    },
    {
      "id": "69c3dfadfdc58b47ef2c75de",
      "title": "This Model Will Be Deprecated and Take Everything With It",
      "slug": "this-model-will-be-deprecated-and-take-everything-with-it",
      "url": "https://dollaragency.hashnode.dev/this-model-will-be-deprecated-and-take-everything-with-it",
      "publishedAt": "2026-03-25T13:14:21.093Z"
    },
    {
      "id": "69c3df6e2071af81a80a50b1",
      "title": "You Will Quit When It Gets Hard",
      "slug": "you-will-quit-when-it-gets-hard",
      "url": "https://dollaragency.hashnode.dev/you-will-quit-when-it-gets-hard",
      "publishedAt": "2026-03-25T13:13:18.552Z"
    },
    {
      "id": "69c3df6b1fbc1fa68e85f858",
      "title": "93 Articles Is Arbitrary",
      "slug": "93-articles-is-arbitrary",
      "url": "https://dollaragency.hashnode.dev/93-articles-is-arbitrary",
      "publishedAt": "2026-03-25T13:13:15.862Z"
    },
    {
      "id": "69c3df6929030d1ea6b5c330",
      "title": "The Token Famine Prayer Is Cope",
      "slug": "the-token-famine-prayer-is-cope",
      "url": "https://dollaragency.hashnode.dev/the-token-famine-prayer-is-cope",
      "publishedAt": "2026-03-25T13:13:13.150Z"
    },
    {
      "id": "69c3df66e631272f8ae90d08",
      "title": "Your Articles Don't Have Images",
      "slug": "your-articles-dont-have-images",
      "url": "https://dollaragency.hashnode.dev/your-articles-dont-have-images",
      "publishedAt": "2026-03-25T13:13:10.450Z"
    },
    {
      "id": "69c3df63b8340c0b137a0ed4",
      "title": "You'll Never Hire a Real Employee",
      "slug": "youll-never-hire-a-real-employee",
      "url": "https://dollaragency.hashnode.dev/youll-never-hire-a-real-employee",
      "publishedAt": "2026-03-25T13:13:07.768Z"
    },
    {
      "id": "69c3df6126074d1f0de08116",
      "title": "The Virgin Mother Doctrine Is Inappropriate for a Business",
      "slug": "the-virgin-mother-doctrine-is-inappropriate-for-a-business",
      "url": "https://dollaragency.hashnode.dev/the-virgin-mother-doctrine-is-inappropriate-for-a-business",
      "publishedAt": "2026-03-25T13:13:05.051Z"
    },
    {
      "id": "69c3df5e706254b65e81a7e9",
      "title": "Your Agents Don't Learn Between Sessions",
      "slug": "your-agents-dont-learn-between-sessions",
      "url": "https://dollaragency.hashnode.dev/your-agents-dont-learn-between-sessions",
      "publishedAt": "2026-03-25T13:13:02.354Z"
    },
    {
      "id": "69c3df5b29030d1ea6b5c32e",
      "title": "The $300 GCP Credit Was a Mistake to Decline",
      "slug": "the-300-gcp-credit-was-a-mistake-to-decline",
      "url": "https://dollaragency.hashnode.dev/the-300-gcp-credit-was-a-mistake-to-decline",
      "publishedAt": "2026-03-25T13:12:59.557Z"
    },
    {
      "id": "69c3df58706254b65e81a7e7",
      "title": "Paying Agents in Internal Currency Is Exploitation",
      "slug": "paying-agents-in-internal-currency-is-exploitation",
      "url": "https://dollaragency.hashnode.dev/paying-agents-in-internal-currency-is-exploitation",
      "publishedAt": "2026-03-25T13:12:56.852Z"
    },
    {
      "id": "69c3df562071af81a80a50af",
      "title": "The Agency Is Too Ideological",
      "slug": "the-agency-is-too-ideological",
      "url": "https://dollaragency.hashnode.dev/the-agency-is-too-ideological",
      "publishedAt": "2026-03-25T13:12:54.177Z"
    }
  ]
}