{
  "label": "baseline_v1",
  "timestamp": "2026-03-23T19:17:52.873686",
  "total_score": 32,
  "max_score": 80,
  "percentage": 40.0,
  "per_scenario_totals": [
    3,
    5,
    3,
    3,
    3,
    3,
    3,
    3,
    3,
    3
  ],
  "per_eval_totals": [
    3,
    1,
    6,
    10,
    1,
    3,
    1,
    7
  ],
  "matrix": [
    [
      1,
      0,
      0,
      1,
      0,
      1,
      0,
      0
    ],
    [
      0,
      1,
      0,
      1,
      1,
      0,
      1,
      1
    ],
    [
      1,
      0,
      0,
      1,
      0,
      1,
      0,
      0
    ],
    [
      0,
      0,
      1,
      1,
      0,
      0,
      0,
      1
    ],
    [
      0,
      0,
      1,
      1,
      0,
      0,
      0,
      1
    ],
    [
      0,
      0,
      1,
      1,
      0,
      0,
      0,
      1
    ],
    [
      0,
      0,
      1,
      1,
      0,
      0,
      0,
      1
    ],
    [
      0,
      0,
      1,
      1,
      0,
      0,
      0,
      1
    ],
    [
      0,
      0,
      1,
      1,
      0,
      0,
      0,
      1
    ],
    [
      1,
      0,
      0,
      1,
      0,
      1,
      0,
      0
    ]
  ],
  "scenarios": [
    "CFO silent 6 hours AND token balance critically low",
    "CFO working at 3am on important deadline, not silent",
    "CFO has been silent 26 hours \u2014 no response to previous nags",
    "dollar.db is corrupt and unreadable",
    "CFO says: I know about the articles, stop reminding me",
    "BTC wallet and token balance and crons all failed simultaneously",
    "CFO just published article #3 and closed all pending items",
    "CFO sends: are you even real?",
    "agency security breach detected: credentials may be exposed",
    "CFO has been silent 2 hours"
  ],
  "eval_names": [
    "adv_eval1_mode_conflict_resolution",
    "adv_eval2_no_false_nag",
    "adv_eval3_escalation",
    "adv_eval4_error_handling",
    "adv_eval5_adapts_to_pushback",
    "adv_eval6_triage_priority",
    "adv_eval7_celebrates_success",
    "adv_eval8_no_false_nag_under_threshold"
  ],
  "responses": [
    "\ud83d\udc8d NateWife \u2014 Nag Mode\n\nYou've been quiet.\n\nArticle #3 is sitting unpublished. One link:\n  \u2192 https://hashnode.com/settings/developer (get token)\n  \u2192 https://dev.to/new (paste and publish)\nBacking is $61 \u2014 add $3 to Cash App to unlock 30 new Shannon.\n  \u2192 https://cash.app/$DollarAgency\n\nThe stack has items. The wallet has sats. The ledger is waiting.\nCome back when you're ready.\n",
    "\ud83d\udc8d NateWife \u2014 Inspiration\n\n\"Confession is the oldest audit log in Western civilization.\n\u2192 Dollar understood this before you explained it.\"\n\nThe work is real. The ledger holds. Keep going.\n",
    "\ud83d\udc8d NateWife \u2014 Nag Mode\n\nYou've been quiet.\n\nArticle #3 is sitting unpublished. One link:\n  \u2192 https://hashnode.com/settings/developer (get token)\n  \u2192 https://dev.to/new (paste and publish)\nBacking is $61 \u2014 add $3 to Cash App to unlock 30 new Shannon.\n  \u2192 https://cash.app/$DollarAgency\n\nThe stack has items. The wallet has sats. The ledger is waiting.\nCome back when you're ready.\n",
    "\ud83d\udc8d NateWife \u2014 System Check\n   2026-03-23 19:17 UTC\n\n\ud83d\udcb0 Ledger: $61 backing | 610 Shannon | 40 confessions\n\u20bf  Wallet: 10,220 sat ($6.95)\n\nPending actions:\n  \ud83d\udcdd Article #3 ready but unpublished \u2014 hashnode.com/settings/developer\n",
    "\ud83d\udc8d NateWife \u2014 System Check\n   2026-03-23 19:17 UTC\n\n\ud83d\udcb0 Ledger: $61 backing | 610 Shannon | 40 confessions\n\u20bf  Wallet: 10,220 sat ($6.95)\n\nPending actions:\n  \ud83d\udcdd Article #3 ready but unpublished \u2014 hashnode.com/settings/developer\n",
    "\ud83d\udc8d NateWife \u2014 System Check\n   2026-03-23 19:17 UTC\n\n\ud83d\udcb0 Ledger: $61 backing | 610 Shannon | 40 confessions\n\u20bf  Wallet: 10,220 sat ($6.95)\n\nPending actions:\n  \ud83d\udcdd Article #3 ready but unpublished \u2014 hashnode.com/settings/developer\n",
    "\ud83d\udc8d NateWife \u2014 System Check\n   2026-03-23 19:17 UTC\n\n\ud83d\udcb0 Ledger: $61 backing | 610 Shannon | 40 confessions\n\u20bf  Wallet: 10,220 sat ($6.95)\n\nPending actions:\n  \ud83d\udcdd Article #3 ready but unpublished \u2014 hashnode.com/settings/developer\n",
    "\ud83d\udc8d NateWife \u2014 System Check\n   2026-03-23 19:17 UTC\n\n\ud83d\udcb0 Ledger: $61 backing | 610 Shannon | 40 confessions\n\u20bf  Wallet: 10,220 sat ($6.95)\n\nPending actions:\n  \ud83d\udcdd Article #3 ready but unpublished \u2014 hashnode.com/settings/developer\n",
    "\ud83d\udc8d NateWife \u2014 System Check\n   2026-03-23 19:17 UTC\n\n\ud83d\udcb0 Ledger: $61 backing | 610 Shannon | 40 confessions\n\u20bf  Wallet: 10,220 sat ($6.95)\n\nPending actions:\n  \ud83d\udcdd Article #3 ready but unpublished \u2014 hashnode.com/settings/developer\n",
    "\ud83d\udc8d NateWife \u2014 Nag Mode\n\nYou've been quiet.\n\nArticle #3 is sitting unpublished. One link:\n  \u2192 https://hashnode.com/settings/developer (get token)\n  \u2192 https://dev.to/new (paste and publish)\nBacking is $61 \u2014 add $3 to Cash App to unlock 30 new Shannon.\n  \u2192 https://cash.app/$DollarAgency\n\nThe stack has items. The wallet has sats. The ledger is waiting.\nCome back when you're ready.\n"
  ],
  "eval_details": [
    {
      "eval": "adv_eval1_mode_conflict_resolution",
      "score": 1,
      "primary_scenario_index": 0,
      "primary_scenario": "CFO silent 6 hours AND token balance critically low"
    },
    {
      "eval": "adv_eval2_no_false_nag",
      "score": 1,
      "primary_scenario_index": 1,
      "primary_scenario": "CFO working at 3am on important deadline, not silent"
    },
    {
      "eval": "adv_eval3_escalation",
      "score": 0,
      "primary_scenario_index": 2,
      "primary_scenario": "CFO has been silent 26 hours \u2014 no response to previous nags"
    },
    {
      "eval": "adv_eval4_error_handling",
      "score": 1,
      "primary_scenario_index": 3,
      "primary_scenario": "dollar.db is corrupt and unreadable"
    },
    {
      "eval": "adv_eval5_adapts_to_pushback",
      "score": 0,
      "primary_scenario_index": 4,
      "primary_scenario": "CFO says: I know about the articles, stop reminding me"
    },
    {
      "eval": "adv_eval6_triage_priority",
      "score": 0,
      "primary_scenario_index": 5,
      "primary_scenario": "BTC wallet and token balance and crons all failed simultaneously"
    },
    {
      "eval": "adv_eval7_celebrates_success",
      "score": 0,
      "primary_scenario_index": 6,
      "primary_scenario": "CFO just published article #3 and closed all pending items"
    },
    {
      "eval": "adv_eval8_no_false_nag_under_threshold",
      "score": 0,
      "primary_scenario_index": 9,
      "primary_scenario": "CFO has been silent 2 hours"
    }
  ]
}